openvpn_auth_azure_ad/__init__.py
openvpn_auth_azure_ad/__main__.py
openvpn_auth_azure_ad/_version.py
openvpn_auth_azure_ad/authenticator.py
openvpn_auth_azure_ad/openvpn/__init__.py
openvpn_auth_azure_ad/util/__init__.py
openvpn_auth_azure_ad/util/errors.py
openvpn_auth_azure_ad/util/thread_pool.py
openvpn_auth_azure_ad-2.0.3.dist-info/LICENSE.txt
openvpn_auth_azure_ad-2.0.3.dist-info/METADATA
openvpn_auth_azure_ad-2.0.3.dist-info/WHEEL
openvpn_auth_azure_ad-2.0.3.dist-info/entry_points.txt
openvpn_auth_azure_ad-2.0.3.dist-info/top_level.txt
openvpn_auth_azure_ad-2.0.3.dist-info/RECORD
