Metadata-Version: 2.1
Name: openvpn-auth-azure-ad
Version: 2.0.3
Summary: openvpn-auth-azure-ad connects to the openvpn management interface and handle the authentication ageist Azure AD.
Home-page: https://github.com/jkroepke/openvpn-auth-azure-ad
Author: Jan-Otto Kröpke
Author-email: pip@jkroepke.de
Project-URL: Changelog, https://github.com/jkroepke/openvpn-auth-azure-ad/blob/main/CHANGELOG.md
Project-URL: Source, https://github.com/jkroepke/openvpn-auth-azure-ad
Project-URL: Bug Reports, https://github.com/jkroepke/openvpn-auth-azure-ad/issues
Keywords: OpenVPN AzureAD authentication
Classifier: Programming Language :: Python :: 3
Classifier: License :: OSI Approved :: MIT License
Classifier: Operating System :: OS Independent
Classifier: Development Status :: 5 - Production/Stable
Classifier: Environment :: Console
Classifier: Topic :: System :: Systems Administration :: Authentication/Directory
License-File: LICENSE.txt
Requires-Dist: msal (~=1.20)
Requires-Dist: cacheout (~=0.14)
Requires-Dist: typer (~=0.7)
Requires-Dist: prometheus-client (~=0.15)
Requires-Dist: concurrent-log-handler (~=0.9)
Requires-Dist: ConfigArgParse (~=1.5)
